cdk_athena_workgroup/__init__.py
cdk_athena_workgroup/py.typed
cdk_athena_workgroup/_jsii/__init__.py
cdk_athena_workgroup/_jsii/cdk-athena-workgroup@1.0.0.jsii.tgz
cdk_athena_workgroup-1.0.0.dist-info/METADATA
cdk_athena_workgroup-1.0.0.dist-info/WHEEL
cdk_athena_workgroup-1.0.0.dist-info/top_level.txt
cdk_athena_workgroup-1.0.0.dist-info/RECORD
