Metadata-Version: 2.1
Name: cdk-athena-workgroup
Version: 1.0.0
Summary: CDK Construct for creating Athena WorkGroups
Home-page: https://github.com/udondan/cdk-athena-workgroup
Author: Daniel Schroeder
License: Apache-2.0
Project-URL: Source, https://github.com/udondan/cdk-athena-workgroup.git
Platform: UNKNOWN
Classifier: Intended Audience :: Developers
Classifier: Operating System :: OS Independent
Classifier: Programming Language :: JavaScript
Classifier: Programming Language :: Python :: 3 :: Only
Classifier: Programming Language :: Python :: 3.6
Classifier: Programming Language :: Python :: 3.7
Classifier: Programming Language :: Python :: 3.8
Classifier: Typing :: Typed
Classifier: Development Status :: 5 - Production/Stable
Classifier: License :: OSI Approved
Requires-Python: >=3.6
Requires-Dist: jsii (<2.0.0,>=1.8.0)
Requires-Dist: publication (>=0.0.3)
Requires-Dist: aws-cdk.aws-cloudformation (<2.0.0,>=1.50.0)
Requires-Dist: aws-cdk.aws-iam (<2.0.0,>=1.50.0)
Requires-Dist: aws-cdk.aws-lambda (<2.0.0,>=1.50.0)
Requires-Dist: aws-cdk.core (<2.0.0,>=1.50.0)
Requires-Dist: constructs (<4.0.0,>=3.0.4)
Requires-Dist: iam-floyd (<0.21.0,>=0.20.0)
